{
	"cmake" : 
	{
		"generator" : 
		{
			"multiConfig" : false,
			"name" : "Ninja"
		},
		"paths" : 
		{
			"cmake" : "D:/SFML_Libs/cmake-3.24/bin/cmake.exe",
			"cpack" : "D:/SFML_Libs/cmake-3.24/bin/cpack.exe",
			"ctest" : "D:/SFML_Libs/cmake-3.24/bin/ctest.exe",
			"root" : "D:/SFML_Libs/cmake-3.24/share/cmake-3.24"
		},
		"version" : 
		{
			"isDirty" : false,
			"major" : 3,
			"minor" : 24,
			"patch" : 3,
			"string" : "3.24.3",
			"suffix" : ""
		}
	},
	"objects" : 
	[
		{
			"jsonFile" : "codemodel-v2-461e1d137bf3acbb03f3.json",
			"kind" : "codemodel",
			"version" : 
			{
				"major" : 2,
				"minor" : 4
			}
		},
		{
			"jsonFile" : "cache-v2-995a3bca87efc7f49230.json",
			"kind" : "cache",
			"version" : 
			{
				"major" : 2,
				"minor" : 0
			}
		},
		{
			"jsonFile" : "cmakeFiles-v1-e25382a317cb7913b946.json",
			"kind" : "cmakeFiles",
			"version" : 
			{
				"major" : 1,
				"minor" : 0
			}
		}
	],
	"reply" : 
	{
		"client-agp" : 
		{
			"cache-v2" : 
			{
				"jsonFile" : "cache-v2-995a3bca87efc7f49230.json",
				"kind" : "cache",
				"version" : 
				{
					"major" : 2,
					"minor" : 0
				}
			},
			"cmakeFiles-v1" : 
			{
				"jsonFile" : "cmakeFiles-v1-e25382a317cb7913b946.json",
				"kind" : "cmakeFiles",
				"version" : 
				{
					"major" : 1,
					"minor" : 0
				}
			},
			"codemodel-v2" : 
			{
				"jsonFile" : "codemodel-v2-461e1d137bf3acbb03f3.json",
				"kind" : "codemodel",
				"version" : 
				{
					"major" : 2,
					"minor" : 4
				}
			}
		}
	}
}
